checker/__init__.py
checker/complexity.py
checker/report.py
tests/__init__.py
tests/test_complexity.py
code_complexity_checker-0.1.10.dist-info/LICENSE
code_complexity_checker-0.1.10.dist-info/METADATA
code_complexity_checker-0.1.10.dist-info/WHEEL
code_complexity_checker-0.1.10.dist-info/entry_points.txt
code_complexity_checker-0.1.10.dist-info/top_level.txt
code_complexity_checker-0.1.10.dist-info/RECORD
