Metadata-Version: 2.1
Name: code-complexity-checker
Version: 0.1.10
Summary: A simple Python tool to calculate code complexity.
Home-page: https://github.com/sneha30404/code-complexity-checker
Author: Sneha
Author-email: sneha30404@gmail.com
Classifier: Programming Language :: Python :: 3
Classifier: License :: OSI Approved :: MIT License
Classifier: Operating System :: OS Independent
Requires-Python: >=3.7
License-File: LICENSE
Requires-Dist: radon>=5.1.0
